rosnik/__init__.py
rosnik/api.py
rosnik/client.py
rosnik/config.py
rosnik/constants.py
rosnik/events/queue.py
rosnik/events/user.py
rosnik/frameworks/django.py
rosnik/frameworks/flask_rosnik.py
rosnik/headers.py
rosnik/providers/openai.py
rosnik/providers/openai_v1.py
rosnik/state.py
rosnik/types/ai.py
rosnik/types/core.py
rosnik/types/user.py
rosnik/wrap.py
rosnik-0.0.37.dist-info/LICENSE
rosnik-0.0.37.dist-info/METADATA
rosnik-0.0.37.dist-info/WHEEL
rosnik-0.0.37.dist-info/RECORD
