Metadata-Version: 2.1
Name: rosnik
Version: 0.0.37
Summary: ROSNIK Python SDK
License: MIT
Author: Nick DiRienzo
Author-email: nick@rosnik.ai
Requires-Python: >=3.10,<4
Classifier: License :: OSI Approved :: MIT License
Classifier: Programming Language :: Python :: 3
Classifier: Programming Language :: Python :: 3.10
Classifier: Programming Language :: Python :: 3.11
Classifier: Programming Language :: Python :: 3.12
Provides-Extra: django
Provides-Extra: flask
Provides-Extra: openai
Requires-Dist: dataclasses-json (>=0.6.1,<0.7.0)
Requires-Dist: django (>=4,<5) ; extra == "django"
Requires-Dist: flask (>=3,<4) ; extra == "flask"
Requires-Dist: openai (>=1,<2) ; extra == "openai"
Requires-Dist: requests (>=2.31.0,<3.0.0)
Requires-Dist: ulid-py (>=1.1.0,<2.0.0)
Requires-Dist: urllib3 (>=2.0.6,<3.0.0)
Requires-Dist: wrapt (>=1.15.0,<2.0.0)
